tensorflow_datasets_ko/__init__.py
tensorflow_datasets_ko/text/__init__.py
tensorflow_datasets_ko/text/c4ko.py
tensorflow_datasets_ko/text/c4ko_test.py
tensorflow_datasets_ko-0.2.3.dist-info/LICENSE
tensorflow_datasets_ko-0.2.3.dist-info/METADATA
tensorflow_datasets_ko-0.2.3.dist-info/WHEEL
tensorflow_datasets_ko-0.2.3.dist-info/top_level.txt
tensorflow_datasets_ko-0.2.3.dist-info/RECORD
