Metadata-Version: 2.1
Name: tensorflow-datasets-ko
Version: 0.2.3
Summary: Custom TensorFlow Datasets for Korean Text Data
Home-page: https://github.com/chrisjihee/tensorflow-datasets-ko
Author: Jihee Ryu
Author-email: chrisjihee@etri.re.kr
License: UNKNOWN
Download-URL: https://github.com/chrisjihee/tensorflow-datasets-ko/archive/v0.2.3.tar.gz
Keywords: TensorFlow,Dataset,C4,Korean,Python
Platform: UNKNOWN
Classifier: Programming Language :: Python :: 3
Classifier: Programming Language :: Python :: 3.6
Classifier: Programming Language :: Python :: 3.7
Classifier: Programming Language :: Python :: 3.8
Classifier: Topic :: Scientific/Engineering :: Artificial Intelligence
Classifier: Topic :: Software Development :: Libraries :: Python Modules
Requires-Python: >=3.6
Requires-Dist: tensorflow-datasets
